cherry_pipelines/__init__.py
cherry_pipelines/config.py
cherry_pipelines/db.py
cherry_pipelines/evm/__init__.py
cherry_pipelines/evm/chain_id.py
cherry_pipelines/evm/chain_name.py
cherry_pipelines/evm/erc20_transfers.py
cherry_pipelines/evm/pipeline.py
cherry_pipelines/svm/__init__.py
cherry_pipelines/svm/common_signatures.py
cherry_pipelines/svm/meteora_swaps.py
cherry_pipelines/svm/orca_metadata.py
cherry_pipelines/svm/orca_swaps.py
cherry_pipelines/svm/pipeline.py
cherry_pipelines/svm/raydium_swaps.py
cherry_pipelines/svm/swap_prices.py
cherry_pipelines/svm/token_decimals.py
cherry_pipelines-0.0.20.dist-info/METADATA
cherry_pipelines-0.0.20.dist-info/WHEEL
cherry_pipelines-0.0.20.dist-info/licenses/LICENSE-APACHE
cherry_pipelines-0.0.20.dist-info/licenses/LICENSE-MIT
cherry_pipelines-0.0.20.dist-info/RECORD
