Metadata-Version: 2.4
Name: cherry-pipelines
Version: 0.0.20
Summary: A collection of blockchain data pipelines built with cherry
License-Expression: MIT OR Apache-2.0
License-File: LICENSE-APACHE
License-File: LICENSE-MIT
Requires-Python: >=3.11
Requires-Dist: cherry-core>=0.6.1
Requires-Dist: cherry-etl>=0.8.0
Requires-Dist: clickhouse-connect>=0.8.17
Requires-Dist: dotenv>=0.9.9
Requires-Dist: pyarrow-stubs>=19.3
Requires-Dist: pyarrow>=20.0.0
